upload_post/__init__.py
upload_post/api_client.py
upload_post/cli.py
upload_post-0.1.2.dist-info/METADATA
upload_post-0.1.2.dist-info/WHEEL
upload_post-0.1.2.dist-info/entry_points.txt
upload_post-0.1.2.dist-info/top_level.txt
upload_post-0.1.2.dist-info/RECORD
