Metadata-Version: 2.4
Name: upload-post
Version: 0.1.2
Summary: Python client for Upload-Post.com API
Home-page: https://www.upload-post.com/
Author: Manuel Gracia
Author-email: hi@img2html.com
Classifier: Programming Language :: Python :: 3
Classifier: License :: OSI Approved :: MIT License
Classifier: Operating System :: OS Independent
Requires-Python: >=3.8
Requires-Dist: requests>=2.25.1
Requires-Dist: python-dotenv>=0.19.0
Dynamic: author
Dynamic: author-email
Dynamic: classifier
Dynamic: description
Dynamic: description-content-type
Dynamic: home-page
Dynamic: requires-dist
Dynamic: requires-python
Dynamic: summary
